Metadata-Version: 2.1
Name: wavechart
Version: 0.0.2
Summary: some utils to show audio wave
Home-page: https://github.com/lixk/WaveChart
Author: Xiangkui Li
Author-email: 1749498702@qq.com
License: MIT Licence
Keywords: pip,wavechart
Platform: any
